SleekQL/SleekQL.py
SleekQL/__init__.py
sleekql-1.0.0.dist-info/LICENSE
sleekql-1.0.0.dist-info/METADATA
sleekql-1.0.0.dist-info/WHEEL
sleekql-1.0.0.dist-info/top_level.txt
sleekql-1.0.0.dist-info/RECORD
