Metadata-Version: 2.1
Name: sleekql
Version: 1.0.0
Summary: A light SQLite3 wrapper for easier database operations in Python.
Home-page: https://github.com/jstiin/sleekql
Author: jstiin
License: AGPL-3.0-only
Keywords: sqlite sqlite3 database wrapper orm sleekql
Classifier: Programming Language :: Python :: 3
Classifier: License :: OSI Approved :: GNU Affero General Public License v3
Classifier: Operating System :: OS Independent
Classifier: Topic :: Database :: Database Engines/Servers
Requires-Python: >=3.7
License-File: LICENSE
